setup.cfg
setup.py
cairomovie/__init__.py
cairomovie/anim.py
cairomovie.egg-info/PKG-INFO
cairomovie.egg-info/SOURCES.txt
cairomovie.egg-info/dependency_links.txt
cairomovie.egg-info/not-zip-safe
cairomovie.egg-info/requires.txt
cairomovie.egg-info/top_level.txt