Metadata-Version: 1.1
Name: cairomovie
Version: 0.8.1
Summary: CSS colors and parsing.
Home-page: http://github.com/idmillington/cairomovie
Author: Ian Millington
Author-email: idmillington@googlemail.com
License: UNKNOWN
Download-URL: https://github.com/idmillington/cairomovie/tarball/master
Keywords: cairomovie,cairo,pymovie
Platform: UNKNOWN
Classifier: Programming Language :: Python :: 3
Classifier: Development Status :: 4 - Beta
Classifier: Environment :: Console
Classifier: Intended Audience :: Developers
Classifier: License :: OSI Approved :: MIT License
Classifier: Operating System :: OS Independent
Classifier: Topic :: Multimedia :: Graphics
